dtools/iterables.py
dtools_iterables-2.0.0.dist-info/licenses/LICENSE
dtools_iterables-2.0.0.dist-info/WHEEL
dtools_iterables-2.0.0.dist-info/METADATA
dtools_iterables-2.0.0.dist-info/RECORD
