Metadata-Version: 2.4
Name: dtools.iterables
Version: 2.0.0
Summary: Module fp.iterables - Iterator related tools
Keywords: iterables,iterators
Author-email: "Geoffrey R. Scheller" <geoffrey@scheller.com>
Requires-Python: >=3.12
Classifier: Development Status :: 5 - Production/Stable
Classifier: Framework :: Pytest
Classifier: Intended Audience :: Developers
Classifier: License :: OSI Approved :: Apache Software License
Classifier: Operating System :: OS Independent
Classifier: Programming Language :: Python :: 3.13
Classifier: Typing :: Typed
License-File: LICENSE
Requires-Dist: dtools.circular-array>=3.15.0, <3.16
Requires-Dist: dtools.containers >=1.0.0, <1.1
Requires-Dist: dtools.fp >=2.0.0, <2.1
Requires-Dist: pytest >=8.3.5 ; extra == "test"
Project-URL: Changelog, https://github.com/grscheller/dtools-iterables/blob/main/CHANGELOG.md
Project-URL: Documentation, https://grscheller.github.io/dtools-namespace-projects/iterables
Project-URL: Homepage, https://github.com/grscheller/dtools-namespace-projects/blob/main/README.md
Project-URL: Source, https://github.com/grscheller/dtools-iterables
Provides-Extra: test
